{
  "id": "necromancer_wail_of_the_dead",
  "name": "Wail of the Dead",
  "school": "Necromancer",
  "rarity": "Rare",
  "top": {
    "name": "Wail of the Dead",
    "mana": 3,
    "speed": "Instant",
    "rules_text": "All enemies within 2 tiles of any undead you control take 3 damage and are pushed 1 tile away.",
    "targeting": {
      "type": "aoe",
      "radius": 2,
      "enemies_only": true
    },
    "effect": {
      "type": "sequence",
      "steps": [
        {
          "type": "damage",
          "amount": 4
        },
        {
          "type": "move",
          "tiles": 1
        }
      ]
    },
    "channel": {
      "name": "Wail of the Dead (Channel)",
      "mana": 3,
      "speed": "Reaction",
      "rules_text": "Channel: Also immobilize pushed enemies for 1 turn",
      "targeting": {
        "type": "unit",
        "range": 6,
        "los": false,
        "enemies_only": true
      },
      "effect": {
        "type": "empty"
      }
    }
  },
  "bottom": {
    "name": "Ossuary",
    "mana": 2,
    "speed": "Sorcery",
    "rules_text": "Imbue target tile: corpses within 2 tiles of this tile auto-raise as skeletons (6HP 3DMG) at start of your turn. Lasts 3 turns.",
    "targeting": {
      "type": "tile",
      "range": 4
    },
    "effect": {
      "type": "sequence",
      "steps": [
        {
          "type": "empty"
        },
        {
          "type": "empty"
        }
      ]
    },
    "channel": {
      "name": "Ossuary (Channel)",
      "mana": 2,
      "speed": "Reaction",
      "rules_text": "Channel: Skeletons raised this way have +1HP",
      "targeting": {
        "type": "tile",
        "range": 4
      },
      "effect": {
        "type": "empty"
      }
    }
  }
}